py3o.renderclient-0.3-py2.7-nspkg.pth
py3o.renderclient-0.3.dist-info/DESCRIPTION.rst
py3o.renderclient-0.3.dist-info/top_level.txt
py3o.renderclient-0.3.dist-info/zip-safe
py3o.renderclient-0.3.dist-info/METADATA
py3o.renderclient-0.3.dist-info/RECORD
py3o.renderclient-0.3.dist-info/WHEEL
py3o.renderclient-0.3.dist-info/metadata.json
py3o.renderclient-0.3.dist-info/namespace_packages.txt
py3o.renderclient-0.3.dist-info/entry_points.txt
py3o/renderclient/client.py
py3o/renderclient/__init__.py
