Metadata-Version: 2.0
Name: py3o.renderclient
Version: 0.3
Summary: transform libreoffice documents to supported formats
Home-page: UNKNOWN
Author: Florent Aide
Author-email: florent.aide@gmail.com
License: BSD License
Keywords: LibreOffice OpenOffice PDF
Platform: UNKNOWN
Classifier: Programming Language :: Python
Classifier: Topic :: Software Development :: Libraries :: Python Modules
Requires-Dist: setuptools
Requires-Dist: pyf.station
Requires-Dist: pyjon.utils
